{
    "profession": "librarian",
    "trades": {
        "novice": [
            {
                "type": "numismatic-overhaul:sell_stack",
                "villager_experience": 1,
                "price_multiplier": 0.0,
                "max_uses": 2,
                "price": 32,
                "sell": {
                    "item": "minecraft:ink_sac",
                    "count": 32
                }
            },
            {
                "type": "numismatic-overhaul:buy_item",
                "villager_experience": 1,
                "price_multiplier": 0.0,
                "max_uses": 2,
                "price": 10,
                "buy": {
                    "item": "minecraft:ink_sac",
                    "count": 32
                }
            },
            {
                "type": "numismatic-overhaul:sell_stack",
                "villager_experience": 1,
                "price_multiplier": 0.0,
                "max_uses": 2,
                "price": 90,
                "sell": {
                    "item": "minecraft:book",
                    "count": 3
                }
            },
            {
                "type": "numismatic-overhaul:sell_stack",
                "villager_experience": 2,
                "price_multiplier": 0.0,
                "max_uses": 2,
                "price": 315,
                "sell": {
                    "item": "minecraft:map",
                    "count": 1
                }
            },
            {
                "type": "numismatic-overhaul:sell_stack",
                "villager_experience": 1,
                "price_multiplier": 0.0,
                "max_uses": 2,
                "price": 48,
                "sell": {
                    "item": "farmersdelight:full_tatami_mat",
                    "count": 4
                }
            },
            {
                "type": "numismatic-overhaul:sell_stack",
                "villager_experience": 15,
                "price_multiplier": 0.0,
                "max_uses": 1,
                "price": 2500,
                "sell": {
                    "item": "minecraft:enchanted_book",
                    "count": 1,
                    "tag": {
                        "StoredEnchantments": [
                            {
                                "id": "additionz:dexterity",
                                "lvl": 1
                            }
                        ]
                    }
                }
            }
        ],
        "apprentice": [
            {
                "type": "numismatic-overhaul:sell_stack",
                "villager_experience": 2,
                "price_multiplier": 0.0,
                "max_uses": 2,
                "price": 100,
                "sell": {
                    "item": "minecraft:bookshelf",
                    "count": 1
                }
            },
            {
                "type": "numismatic-overhaul:sell_stack",
                "villager_experience": 4,
                "price_multiplier": 0.0,
                "max_uses": 1,
                "price": 160,
                "sell": {
                    "item": "minecraft:flint_and_steel",
                    "count": 1
                }
            },
            {
                "type": "numismatic-overhaul:buy_item",
                "villager_experience": 4,
                "price_multiplier": 0.0,
                "max_uses": 1,
                "price": 55,
                "buy": {
                    "item": "minecraft:flint_and_steel",
                    "count": 1
                }
            },
            {
                "type": "numismatic-overhaul:sell_stack",
                "villager_experience": 2,
                "price_multiplier": 0.0,
                "max_uses": 1,
                "price": 48,
                "sell": {
                    "item": "farmersdelight:canvas",
                    "count": 8
                }
            },
            {
                "type": "numismatic-overhaul:buy_item",
                "villager_experience": 2,
                "price_multiplier": 0.0,
                "max_uses": 1,
                "price": 16,
                "buy": {
                    "item": "farmersdelight:canvas",
                    "count": 8
                }
            },
            {
                "type": "numismatic-overhaul:sell_stack",
                "villager_experience": 2,
                "price_multiplier": 0.0,
                "max_uses": 1,
                "price": 96,
                "sell": {
                    "item": "farmersdelight:canvas_sign",
                    "count": 8
                }
            },
            {
                "type": "numismatic-overhaul:buy_item",
                "villager_experience": 2,
                "price_multiplier": 0.0,
                "max_uses": 1,
                "price": 24,
                "buy": {
                    "item": "farmersdelight:canvas_sign",
                    "count": 8
                }
            },
            {
                "type": "numismatic-overhaul:sell_stack",
                "villager_experience": 2,
                "price_multiplier": 0.0,
                "max_uses": 1,
                "price": 96,
                "sell": {
                    "item": "farmersdelight:white_canvas_sign",
                    "count": 8
                }
            },
            {
                "type": "numismatic-overhaul:buy_item",
                "villager_experience": 2,
                "price_multiplier": 0.0,
                "max_uses": 1,
                "price": 24,
                "buy": {
                    "item": "farmersdelight:white_canvas_sign",
                    "count": 8
                }
            },
            {
                "type": "numismatic-overhaul:sell_stack",
                "villager_experience": 2,
                "price_multiplier": 0.0,
                "max_uses": 1,
                "price": 96,
                "sell": {
                    "item": "farmersdelight:orange_canvas_sign",
                    "count": 8
                }
            },
            {
                "type": "numismatic-overhaul:buy_item",
                "villager_experience": 2,
                "price_multiplier": 0.0,
                "max_uses": 1,
                "price": 24,
                "buy": {
                    "item": "farmersdelight:orange_canvas_sign",
                    "count": 8
                }
            },
            {
                "type": "numismatic-overhaul:sell_stack",
                "villager_experience": 2,
                "price_multiplier": 0.0,
                "max_uses": 1,
                "price": 96,
                "sell": {
                    "item": "farmersdelight:magenta_canvas_sign",
                    "count": 8
                }
            },
            {
                "type": "numismatic-overhaul:buy_item",
                "villager_experience": 2,
                "price_multiplier": 0.0,
                "max_uses": 1,
                "price": 24,
                "buy": {
                    "item": "farmersdelight:magenta_canvas_sign",
                    "count": 8
                }
            },
            {
                "type": "numismatic-overhaul:sell_stack",
                "villager_experience": 2,
                "price_multiplier": 0.0,
                "max_uses": 1,
                "price": 96,
                "sell": {
                    "item": "farmersdelight:light_blue_canvas_sign",
                    "count": 8
                }
            },
            {
                "type": "numismatic-overhaul:buy_item",
                "villager_experience": 2,
                "price_multiplier": 0.0,
                "max_uses": 1,
                "price": 24,
                "buy": {
                    "item": "farmersdelight:light_blue_canvas_sign",
                    "count": 8
                }
            },
            {
                "type": "numismatic-overhaul:sell_stack",
                "villager_experience": 2,
                "price_multiplier": 0.0,
                "max_uses": 1,
                "price": 96,
                "sell": {
                    "item": "farmersdelight:yellow_canvas_sign",
                    "count": 8
                }
            },
            {
                "type": "numismatic-overhaul:buy_item",
                "villager_experience": 2,
                "price_multiplier": 0.0,
                "max_uses": 1,
                "price": 24,
                "buy": {
                    "item": "farmersdelight:yellow_canvas_sign",
                    "count": 8
                }
            },
            {
                "type": "numismatic-overhaul:sell_stack",
                "villager_experience": 2,
                "price_multiplier": 0.0,
                "max_uses": 1,
                "price": 96,
                "sell": {
                    "item": "farmersdelight:lime_canvas_sign",
                    "count": 8
                }
            },
            {
                "type": "numismatic-overhaul:buy_item",
                "villager_experience": 2,
                "price_multiplier": 0.0,
                "max_uses": 1,
                "price": 24,
                "buy": {
                    "item": "farmersdelight:lime_canvas_sign",
                    "count": 8
                }
            },
            {
                "type": "numismatic-overhaul:sell_stack",
                "villager_experience": 2,
                "price_multiplier": 0.0,
                "max_uses": 1,
                "price": 96,
                "sell": {
                    "item": "farmersdelight:pink_canvas_sign",
                    "count": 8
                }
            },
            {
                "type": "numismatic-overhaul:buy_item",
                "villager_experience": 2,
                "price_multiplier": 0.0,
                "max_uses": 1,
                "price": 24,
                "buy": {
                    "item": "farmersdelight:pink_canvas_sign",
                    "count": 8
                }
            },
            {
                "type": "numismatic-overhaul:sell_stack",
                "villager_experience": 2,
                "price_multiplier": 0.0,
                "max_uses": 1,
                "price": 96,
                "sell": {
                    "item": "farmersdelight:gray_canvas_sign",
                    "count": 8
                }
            },
            {
                "type": "numismatic-overhaul:buy_item",
                "villager_experience": 2,
                "price_multiplier": 0.0,
                "max_uses": 1,
                "price": 24,
                "buy": {
                    "item": "farmersdelight:gray_canvas_sign",
                    "count": 8
                }
            },
            {
                "type": "numismatic-overhaul:sell_stack",
                "villager_experience": 2,
                "price_multiplier": 0.0,
                "max_uses": 1,
                "price": 96,
                "sell": {
                    "item": "farmersdelight:light_gray_canvas_sign",
                    "count": 8
                }
            },
            {
                "type": "numismatic-overhaul:buy_item",
                "villager_experience": 2,
                "price_multiplier": 0.0,
                "max_uses": 1,
                "price": 24,
                "buy": {
                    "item": "farmersdelight:light_gray_canvas_sign",
                    "count": 8
                }
            },
            {
                "type": "numismatic-overhaul:sell_stack",
                "villager_experience": 2,
                "price_multiplier": 0.0,
                "max_uses": 1,
                "price": 96,
                "sell": {
                    "item": "farmersdelight:cyan_canvas_sign",
                    "count": 8
                }
            },
            {
                "type": "numismatic-overhaul:buy_item",
                "villager_experience": 2,
                "price_multiplier": 0.0,
                "max_uses": 1,
                "price": 24,
                "buy": {
                    "item": "farmersdelight:cyan_canvas_sign",
                    "count": 8
                }
            },
            {
                "type": "numismatic-overhaul:sell_stack",
                "villager_experience": 2,
                "price_multiplier": 0.0,
                "max_uses": 1,
                "price": 96,
                "sell": {
                    "item": "farmersdelight:purple_canvas_sign",
                    "count": 8
                }
            },
            {
                "type": "numismatic-overhaul:buy_item",
                "villager_experience": 2,
                "price_multiplier": 0.0,
                "max_uses": 1,
                "price": 24,
                "buy": {
                    "item": "farmersdelight:purple_canvas_sign",
                    "count": 8
                }
            },
            {
                "type": "numismatic-overhaul:sell_stack",
                "villager_experience": 2,
                "price_multiplier": 0.0,
                "max_uses": 1,
                "price": 96,
                "sell": {
                    "item": "farmersdelight:blue_canvas_sign",
                    "count": 8
                }
            },
            {
                "type": "numismatic-overhaul:buy_item",
                "villager_experience": 2,
                "price_multiplier": 0.0,
                "max_uses": 1,
                "price": 24,
                "buy": {
                    "item": "farmersdelight:blue_canvas_sign",
                    "count": 8
                }
            },
            {
                "type": "numismatic-overhaul:sell_stack",
                "villager_experience": 2,
                "price_multiplier": 0.0,
                "max_uses": 1,
                "price": 96,
                "sell": {
                    "item": "farmersdelight:brown_canvas_sign",
                    "count": 8
                }
            },
            {
                "type": "numismatic-overhaul:buy_item",
                "villager_experience": 2,
                "price_multiplier": 0.0,
                "max_uses": 1,
                "price": 24,
                "buy": {
                    "item": "farmersdelight:brown_canvas_sign",
                    "count": 8
                }
            },
            {
                "type": "numismatic-overhaul:sell_stack",
                "villager_experience": 2,
                "price_multiplier": 0.0,
                "max_uses": 1,
                "price": 96,
                "sell": {
                    "item": "farmersdelight:green_canvas_sign",
                    "count": 8
                }
            },
            {
                "type": "numismatic-overhaul:buy_item",
                "villager_experience": 2,
                "price_multiplier": 0.0,
                "max_uses": 1,
                "price": 24,
                "buy": {
                    "item": "farmersdelight:green_canvas_sign",
                    "count": 8
                }
            },
            {
                "type": "numismatic-overhaul:sell_stack",
                "villager_experience": 2,
                "price_multiplier": 0.0,
                "max_uses": 1,
                "price": 96,
                "sell": {
                    "item": "farmersdelight:red_canvas_sign",
                    "count": 8
                }
            },
            {
                "type": "numismatic-overhaul:buy_item",
                "villager_experience": 2,
                "price_multiplier": 0.0,
                "max_uses": 1,
                "price": 24,
                "buy": {
                    "item": "farmersdelight:red_canvas_sign",
                    "count": 8
                }
            },
            {
                "type": "numismatic-overhaul:sell_stack",
                "villager_experience": 2,
                "price_multiplier": 0.0,
                "max_uses": 1,
                "price": 96,
                "sell": {
                    "item": "farmersdelight:black_canvas_sign",
                    "count": 8
                }
            },
            {
                "type": "numismatic-overhaul:buy_item",
                "villager_experience": 2,
                "price_multiplier": 0.0,
                "max_uses": 1,
                "price": 24,
                "buy": {
                    "item": "farmersdelight:black_canvas_sign",
                    "count": 8
                }
            },
            {
                "type": "numismatic-overhaul:sell_stack",
                "villager_experience": 15,
                "price_multiplier": 0.0,
                "max_uses": 1,
                "price": 2500,
                "sell": {
                    "item": "minecraft:enchanted_book",
                    "count": 1,
                    "tag": {
                        "StoredEnchantments": [
                            {
                                "id": "minecraft:binding_curse",
                                "lvl": 1
                            }
                        ]
                    }
                }
            },
            {
                "type": "numismatic-overhaul:buy_item",
                "villager_experience": 5,
                "price_multiplier": 0.0,
                "max_uses": 1,
                "price": 500,
                "buy": {
                    "item": "minecraft:enchanted_book",
                    "count": 1,
                    "tag": {
                        "StoredEnchantments": [
                            {
                                "id": "minecraft:binding_curse",
                                "lvl": 1
                            }
                        ]
                    }
                }
            },
            {
                "type": "numismatic-overhaul:sell_stack",
                "villager_experience": 10,
                "price_multiplier": 0.0,
                "max_uses": 1,
                "price": 1250,
                "sell": {
                    "item": "minecraft:enchanted_book",
                    "count": 1,
                    "tag": {
                        "StoredEnchantments": [
                            {
                                "id": "combatroll:multi_roll",
                                "lvl": 1
                            }
                        ]
                    }
                }
            }
        ],
        "journeyman": [
            {
                "type": "numismatic-overhaul:sell_stack",
                "villager_experience": 3,
                "price_multiplier": 0.0,
                "max_uses": 1,
                "price": 36,
                "sell": {
                    "item": "minecraft:writable_book",
                    "count": 1
                }
            },
            {
                "type": "numismatic-overhaul:sell_stack",
                "villager_experience": 3,
                "price_multiplier": 0.0,
                "max_uses": 1,
                "price": 606,
                "sell": {
                    "item": "minecraft:compass",
                    "count": 1
                }
            },
            {
                "type": "numismatic-overhaul:buy_item",
                "villager_experience": 3,
                "price_multiplier": 0.0,
                "max_uses": 1,
                "price": 201,
                "buy": {
                    "item": "minecraft:compass",
                    "count": 1
                }
            },
            {
                "type": "numismatic-overhaul:sell_stack",
                "villager_experience": 6,
                "price_multiplier": 0.0,
                "max_uses": 1,
                "price": 4800,
                "sell": {
                    "item": "betternether:chest_of_drawers",
                    "count": 1
                }
            },
            {
                "type": "numismatic-overhaul:buy_item",
                "villager_experience": 6,
                "price_multiplier": 0.0,
                "max_uses": 1,
                "price": 1600,
                "buy": {
                    "item": "betternether:chest_of_drawers",
                    "count": 1
                }
            },
            {
                "type": "numismatic-overhaul:sell_stack",
                "villager_experience": 3,
                "price_multiplier": 0.0,
                "max_uses": 1,
                "price": 906,
                "sell": {
                    "item": "minecraft:clock",
                    "count": 1
                }
            },
            {
                "type": "numismatic-overhaul:buy_item",
                "villager_experience": 3,
                "price_multiplier": 0.0,
                "max_uses": 1,
                "price": 301,
                "buy": {
                    "item": "minecraft:clock",
                    "count": 1
                }
            },
            {
                "type": "numismatic-overhaul:sell_stack",
                "villager_experience": 15,
                "price_multiplier": 0.0,
                "max_uses": 1,
                "price": 2500,
                "sell": {
                    "item": "minecraft:enchanted_book",
                    "count": 1,
                    "tag": {
                        "StoredEnchantments": [
                            {
                                "id": "combatroll:multi_roll",
                                "lvl": 2
                            }
                        ]
                    }
                }
            },
            {
                "type": "numismatic-overhaul:sell_stack",
                "villager_experience": 20,
                "price_multiplier": 0.0,
                "max_uses": 1,
                "price": 5000,
                "sell": {
                    "item": "minecraft:enchanted_book",
                    "count": 1,
                    "tag": {
                        "StoredEnchantments": [
                            {
                                "id": "additionz:dexterity",
                                "lvl": 2
                            }
                        ]
                    }
                }
            }
        ],
        "expert": [
            {
                "type": "numismatic-overhaul:sell_stack",
                "villager_experience": 4,
                "price_multiplier": 0.0,
                "max_uses": 1,
                "price": 45,
                "sell": {
                    "item": "minecraft:spyglass",
                    "count": 1
                }
            },
            {
                "type": "numismatic-overhaul:buy_item",
                "villager_experience": 4,
                "price_multiplier": 0.0,
                "max_uses": 1,
                "price": 15,
                "buy": {
                    "item": "minecraft:spyglass",
                    "count": 1
                }
            },
            {
                "type": "numismatic-overhaul:sell_stack",
                "villager_experience": 4,
                "price_multiplier": 0.0,
                "max_uses": 1,
                "price": 60,
                "sell": {
                    "item": "minecraft:daylight_detector",
                    "count": 1
                }
            },
            {
                "type": "numismatic-overhaul:sell_stack",
                "villager_experience": 15,
                "price_multiplier": 0.0,
                "max_uses": 1,
                "price": 2500,
                "sell": {
                    "item": "minecraft:enchanted_book",
                    "count": 1,
                    "tag": {
                        "StoredEnchantments": [
                            {
                                "id": "minecraft:vanishing_curse",
                                "lvl": 1
                            }
                        ]
                    }
                }
            },
            {
                "type": "numismatic-overhaul:buy_item",
                "villager_experience": 5,
                "price_multiplier": 0.0,
                "max_uses": 1,
                "price": 500,
                "buy": {
                    "item": "minecraft:enchanted_book",
                    "count": 1,
                    "tag": {
                        "StoredEnchantments": [
                            {
                                "id": "minecraft:vanishing_curse",
                                "lvl": 1
                            }
                        ]
                    }
                }
            },
            {
                "type": "numismatic-overhaul:sell_stack",
                "villager_experience": 20,
                "price_multiplier": 0.0,
                "max_uses": 1,
                "price": 5000,
                "sell": {
                    "item": "minecraft:enchanted_book",
                    "count": 1,
                    "tag": {
                        "StoredEnchantments": [
                            {
                                "id": "combatroll:multi_roll",
                                "lvl": 3
                            }
                        ]
                    }
                }
            }
        ],
        "master": [
            {
                "type": "numismatic-overhaul:sell_stack",
                "villager_experience": 10,
                "price_multiplier": 0.0,
                "max_uses": 1,
                "price": 100,
                "sell": {
                    "item": "horseexpert:monocle",
                    "count": 1
                }
            },
            {
                "type": "numismatic-overhaul:sell_stack",
                "villager_experience": 5,
                "price_multiplier": 0.0,
                "max_uses": 1,
                "price": 1086,
                "sell": {
                    "item": "minecraft:recovery_compass",
                    "count": 1
                }
            },
            {
                "type": "numismatic-overhaul:buy_item",
                "villager_experience": 5,
                "price_multiplier": 0.0,
                "max_uses": 1,
                "price": 361,
                "buy": {
                    "item": "minecraft:recovery_compass",
                    "count": 1
                }
            },
            {
                "type": "numismatic-overhaul:sell_stack",
                "villager_experience": 10,
                "price_multiplier": 0.0,
                "max_uses": 1,
                "price": 50000,
                "sell": {
                    "item": "endrem:cursed_eye",
                    "count": 1
                }
            },
            {
                "type": "numismatic-overhaul:sell_stack",
                "villager_experience": 5,
                "price_multiplier": 0.0,
                "max_uses": 1,
                "price": 4200,
                "sell": {
                    "item": "minecraft:name_tag",
                    "count": 1
                }
            },
            {
                "type": "numismatic-overhaul:sell_stack",
                "villager_experience": 25,
                "price_multiplier": 0.0,
                "max_uses": 1,
                "price": 10000,
                "sell": {
                    "item": "minecraft:enchanted_book",
                    "count": 1,
                    "tag": {
                        "StoredEnchantments": [
                            {
                                "id": "combatroll:multi_roll",
                                "lvl": 4
                            }
                        ]
                    }
                }
            },
            {
                "type": "numismatic-overhaul:sell_stack",
                "villager_experience": 25,
                "price_multiplier": 0.0,
                "max_uses": 1,
                "price": 10000,
                "sell": {
                    "item": "minecraft:enchanted_book",
                    "count": 1,
                    "tag": {
                        "StoredEnchantments": [
                            {
                                "id": "additionz:dexterity",
                                "lvl": 3
                            }
                        ]
                    }
                }
            }
        ]
    }
}